[
    {
        "name": "Eduardo André",
        "price": "69,698",
        "detail": "Vera Cruz City, Hong Kong",
        "image": "./r1.png"
    },
    {
        "name": "Eduardo André",
        "price": "69,698",
        "detail": "Vera Cruz City, Hong Kong",
        "image": "./r1.png"
    },
    {
        "name": "Eduardo André",
        "price": "69,698",
        "detail": "Vera Cruz City, Hong Kong",
        "image": "./r1.png"
    },
    {
        "name": "Eduardo André",
        "price": "69,698",
        "detail": "Vera Cruz City, Hong Kong",
        "image": "./r1.png"
    },
    {
        "name": "Eduardo André",
        "price": "69,698",
        "detail": "Vera Cruz City, Hong Kong",
        "image": "./r1.png"
    },
    {
        "name": "Eduardo André",
        "price": "69,698",
        "detail": "Vera Cruz City, Hong Kong",
        "image": "./r1.png"
    },
    {
        "name": "Eduardo André",
        "price": "69,698",
        "detail": "Vera Cruz City, Hong Kong",
        "image": "./r1.png"
    }
]